Workbook

Sheet Read Me
A1: BRUSH → BONZI → A GROWING CHAIN
A2: Economy v0.2 | 11 September 2026 | Blue = editable input • Green = formula • All timings are hypotheses, not observed playtests.
A5: Sheet / topic | B5: Purpose | C5: How to use
A6: Assumptions | B6: Shared economy and scenario inputs. | C6: Change these and blue Shops/Upgrades values. Formula caches are supplied for previews; Excel/LibreOffice recalculates edits.
A7: Shops | B7: Five locations: prices, job rewards, service capacities, local gates. | C7: Shops 1–2 are the slice. Shops 3–5 are placeholders. Zero finishing means the service is not required.
A8: Items | B8: Personal tools and blueprint/build ownership. | C8: Whole blueprints are permanent. Starter and opening kits have no hidden construction cost.
A9: Upgrades | B9: Optional local machine purchases with bottleneck-aware output and payback. | C9: Named before/after scenarios are linked sequentially. Payback is cash-only; parts/gates require extra effort.
A10: Pacing | B10: Sequential progression with cash carried across purchases. | C10: Average-rate model; active job rounding, local manual/auto gates. No optional purchases or offline cap in this sheet.
A11: Starter Routes | B11: Three explicit ways to reach High Street. | C11: Continuous active, 50% activity and minimum manual work followed by absence. Remainder cash retained.
A12: Offline | B12: Eight-hour cap, integer completed deliveries, owned/enabled branches. | C12: Change hours, ownership switches and fractional order progress. S1 enabled means Bonzi has been built.
A13: Blueprints & Parts | B13: Guaranteed unlocks and optional crafting costs. | C13: No fragment currency, random drop requirement, parts from idle, or mandatory parts gate.
A14: UI & States | B14: UI states and transitions for the coming implementation. | C14: Design only; no runtime/UI changes are included.
A15: Checks | B15: Formula checks and default-route simulation results. | C15: Formula checks update with workbook inputs. The discrete route check is a labeled default snapshot.
A16: Scope | B16: Old shops keep earning; first shop free; parts begin in S2. | C16: No energy, rent, gems, chests, prestige, monetization or operating expenses in this model.
... A18: Source of truth | B18: GDD v0.2 gives rules; workbook gives numeric inputs. | C18: Written examples match the initial defaults. If workbook inputs change, update written examples before implementation.

Sheet Assumptions
A1: THE TUNING DESK
A2: Input values apply to the proposed slice. No real-money values. Active fraction describes time spent completing manual jobs while production runs.
A5: Parameter | B5: Value | C5: Unit / meaning | D5: Status
A6: Starting cash | B6: 0 | C6: cash; starter premises and brush already owned | D6: Proposed
A7: Bonzi build cost | B7: 100 | C7: cash; includes first automated chassis | D7: Proposed
A8: Bonzi blueprint at job | B8: 3 | C8: local S1 paid manual completions | D8: Proposed
A9: Offline cap | B9: 8 | C9: hours per absence, not a live production cap | D9: Proposed
A10: Active fraction | B10: 1 | C10: Pacing scenario; >0 to 1. 0 is invalid because manual gates exist. | D10: Scenario
A11: Clump completion | B11: 0.9 | C11: fraction cleared before Finish is allowed; not current toy rule | D11: Proposed
A12: Surface completion | B12: 0.9 | C12: fraction of surface cleaned; must also pass clump check | D12: Proposed
A13: Parts per eligible manual | B13: 1 | C13: integer; S2+ rewarded jobs only | D13: Proposed
A14: Wide Brush build cost | B14: 80 | C14: cash; blueprint at eight S1 manual jobs | D14: Proposed
A15: Wide Brush work seconds | B15: 40 | C15: seconds on the same S1 rug; handling stays unchanged | D15: Unmeasured target
A16: Slow activity scenario | B16: 0.5 | C16: Starter Routes only; after Bonzi | D16: Scenario

Sheet Shops
A2: Opening price includes the tools and local automated unit needed to operate. S1 automation is separately enabled by Bonzi. All rates below assume automation enabled.
A5: ID | B5: Shop | C5: Open cash | D5: Manual cash | E5: Work sec | F5: Handling sec | G5: Demand /h | H5: Cleaner /h | I5: Finish /h (0=N/A) | J5: Routine cash/order | K5: Prev-shop manual gate | L5: Prev-shop auto gate | M5: Identity / opening kit | N5: Scope | O5: Cycle sec | P5: Auto orders/h | Q5: Auto cash/h | R5: Manual cash/h | S5: Chain auto cash/h
A6: S1 | B6: Neighborhood Shop | C6: 0 | D6: 20 | E6: 50 | F6: 10 | G6: 40 | H6: 30 | I6: 0 | J6: 10 | K6: 0 | L6: 0 | M6: Brush; mint/cream tiles | N6: Playable slice | O6: =E6+F6 -> 60 | P6: =MIN(G6,H6,IF(I6=0,H6,I6)) -> 30 | Q6: =P6*J6 -> 300 | R6: =D6*3600/O6 -> 1200 | S6: =SUM(Q$6:Q6) -> 300
A7: S2 | B7: Busy High Street | C7: 600 | D7: 60 | E7: 60 | F7: 10 | G7: 40 | H7: 30 | I7: 36 | J7: 25 | K7: 15 | L7: 5 | M7: Jet + squeegee; coral storefront | N7: Playable slice | O7: =E7+F7 -> 70 | P7: =MIN(G7,H7,IF(I7=0,H7,I7)) -> 30 | Q7: =P7*J7 -> 750 | R7: =D7*3600/O7 -> 3085.7143 | S7: =SUM(Q$6:Q7) -> 1050
A8: S3 | B8: Restoration Studio | C8: 6000 | D8: 150 | E8: 100 | F8: 10 | G8: 36 | H8: 24 | I8: 30 | J8: 65 | K8: 12 | L8: 20 | M8: Treatment + pile kit; indigo/timber | N8: Placeholder | O8: =E8+F8 -> 110 | P8: =MIN(G8,H8,IF(I8=0,H8,I8)) -> 24 | Q8: =P8*J8 -> 1560 | R8: =D8*3600/O8 -> 4909.0909 | S8: =SUM(Q$6:Q8) -> 2610
A9: S4 | B9: Commercial Workshop | C9: 40000 | D9: 350 | E9: 130 | F9: 10 | G9: 36 | H9: 24 | I9: 30 | J9: 175 | K9: 15 | L9: 30 | M9: Broad tools; teal industrial bay | N9: Placeholder | O9: =E9+F9 -> 140 | P9: =MIN(G9,H9,IF(I9=0,H9,I9)) -> 24 | Q9: =P9*J9 -> 4200 | R9: =D9*3600/O9 -> 9000 | S9: =SUM(Q$6:Q9) -> 6810
A10: S5 | B10: Flagship Atelier | C10: 180000 | D10: 900 | E10: 180 | F10: 10 | G10: 30 | H10: 20 | I10: 24 | J10: 450 | K10: 18 | L10: 40 | M10: Integrated rig; cream/gold atelier | N10: Placeholder | O10: =E10+F10 -> 190 | P10: =MIN(G10,H10,IF(I10=0,H10,I10)) -> 20 | Q10: =P10*J10 -> 9000 | R10: =D10*3600/O10 -> 17052.632 | S10: =SUM(Q$6:Q10) -> 15810

Sheet Items
A1: KNOW IT → BUILD IT → USE IT
A2: No duplicate personal tool builds. Opening kits are granted as part of the shop purchase; “included” never means a second bill. Later optional variant prices remain unset.
A5: Item | B5: Unlock / blueprint | C5: Build cash | D5: Parts | E5: Ownership | F5: Effect / boundary
A6: Hand Brush | B6: First launch | C6: 0 | D6: 0 | E6: Account personal tool | F6: Only cleaning tool in the starter economy. Existing prototype display tools stay prototype-only until wet service.
A7: Bonzi + basic chassis | B7: 3 paid S1 manual jobs | C7: =Assumptions!B7 -> 100 | D7: 0 | E7: Named buddy + S1 unit | F7: 30 orders/h capacity. A new unit is bundled with each later shop.
A8: Wide Brush | B8: 8 paid S1 manual jobs | C8: =Assumptions!B14 -> 80 | D8: 0 | E8: Account personal tool | F8: S1 work target 50→40 seconds; no handling change. Optional.
A9: Jet + Hand Squeegee | B9: High Street opening | C9: Included | D9: 0 | E9: Account personal tools | F9: Required wet-service capability. Recipe must function before S2 is playable.
A10: Restoration starter kit | B10: Restoration Studio opening | C10: Included | D10: 0 | E10: Account personal tools | F10: Treatment and pile capability; exact tool interaction is later scope.
A11: Broad cleaning kit | B11: Commercial Workshop opening | C11: Included | D11: 0 | E11: Account personal tools | F11: Wide work surface capability; later scope.
A12: Integrated Rig | B12: Flagship opening | C12: Included | D12: 0 | E12: Account personal tool | F12: Capstone starter capability; later scope.
A13: Foam brush / rake / CRB / rotary variants | B13: Later authored milestones | C13: TBD | D13: TBD | E13: Personal optional variants | F13: Do not price capabilities that are not yet designed. No random required unlocks.
A14: Local modules | B14: See Upgrades and Blueprints & Parts | C14: See Upgrades | D14: See Upgrades | E14: Bound to purchased branch | F14: Incremental one-time named upgrades. No resale or infinite levels.

Sheet Upgrades
A1: SPEND ON THE ACTUAL BOTTLENECK
A2: Rows are named scenarios, not purchases to sum together. Sequential rows inherit the previous output settings. Payback ignores parts acquisition time. Zero gain is shown explicitly.
A5: Scenario / purchase | B5: Cash | C5: Parts | D5: Before demand | E5: Before cleaner | F5: Before finish (0=N/A) | G5: After demand | H5: After cleaner | I5: After finish (0=N/A) | J5: Cash/order | K5: Before orders/h | L5: After orders/h | M5: Before cash/h | N5: After cash/h | O5: Gain cash/h | P5: Cash payback h | Q5: Prerequisite / meaning
A6: S1 Mk II only | B6: 120 | C6: 0 | D6: =Shops!G6 -> 40 | E6: =Shops!H6 -> 30 | F6: =Shops!I6 -> 0 | G6: =D6 -> 40 | H6: 45 | I6: =F6 -> 0 | J6: =Shops!J6 -> 10 | K6: =MIN(D6,E6,IF(F6=0,E6,F6)) -> 30 | L6: =MIN(G6,H6,IF(I6=0,H6,I6)) -> 40 | M6: =K6*J6 -> 300 | N6: =L6*J6 -> 400 | O6: =N6-M6 -> 100 | P6: =IF(O6>0,B6/O6,"No gain") -> 1.2 | Q6: Bonzi + 10 S1 manual jobs; demand becomes bottleneck
A7: S1 intake after Mk II | B7: 100 | C7: 0 | D7: =G6 -> 40 | E7: =H6 -> 45 | F7: =I6 -> 0 | G7: 60 | H7: =E7 -> 45 | I7: =F7 -> 0 | J7: =Shops!J6 -> 10 | K7: =MIN(D7,E7,IF(F7=0,E7,F7)) -> 40 | L7: =MIN(G7,H7,IF(I7=0,H7,I7)) -> 45 | M7: =K7*J7 -> 400 | N7: =L7*J7 -> 450 | O7: =N7-M7 -> 50 | P7: =IF(O7>0,B7/O7,"No gain") -> 2 | Q7: Owned Mk II; cleaner becomes bottleneck
A8: S1 intake BEFORE Mk II | B8: 100 | C8: 0 | D8: =Shops!G6 -> 40 | E8: =Shops!H6 -> 30 | F8: =Shops!I6 -> 0 | G8: 60 | H8: =E8 -> 30 | I8: =F8 -> 0 | J8: =Shops!J6 -> 10 | K8: =MIN(D8,E8,IF(F8=0,E8,F8)) -> 30 | L8: =MIN(G8,H8,IF(I8=0,H8,I8)) -> 30 | M8: =K8*J8 -> 300 | N8: =L8*J8 -> 300 | O8: =N8-M8 -> 0 | P8: =IF(O8>0,B8/O8,"No gain") -> No gain | Q8: Alternative order: no immediate income gain
A9: S2 cleaner module | B9: 900 | C9: 6 | D9: =Shops!G7 -> 40 | E9: =Shops!H7 -> 30 | F9: =Shops!I7 -> 36 | G9: =D9 -> 40 | H9: 45 | I9: =F9 -> 36 | J9: =Shops!J7 -> 25 | K9: =MIN(D9,E9,IF(F9=0,E9,F9)) -> 30 | L9: =MIN(G9,H9,IF(I9=0,H9,I9)) -> 36 | M9: =K9*J9 -> 750 | N9: =L9*J9 -> 900 | O9: =N9-M9 -> 150 | P9: =IF(O9>0,B9/O9,"No gain") -> 6 | Q9: 6 local manual jobs; finishing becomes bottleneck
A10: S2 finish after cleaner | B10: 600 | C10: 4 | D10: =G9 -> 40 | E10: =H9 -> 45 | F10: =I9 -> 36 | G10: =D10 -> 40 | H10: =E10 -> 45 | I10: 48 | J10: =Shops!J7 -> 25 | K10: =MIN(D10,E10,IF(F10=0,E10,F10)) -> 36 | L10: =MIN(G10,H10,IF(I10=0,H10,I10)) -> 40 | M10: =K10*J10 -> 900 | N10: =L10*J10 -> 1000 | O10: =N10-M10 -> 100 | P10: =IF(O10>0,B10/O10,"No gain") -> 6 | Q10: Owned cleaner module; demand becomes bottleneck
A11: S2 intake after both | B11: 750 | C11: 0 | D11: =G10 -> 40 | E11: =H10 -> 45 | F11: =I10 -> 48 | G11: 60 | H11: =E11 -> 45 | I11: =F11 -> 48 | J11: =Shops!J7 -> 25 | K11: =MIN(D11,E11,IF(F11=0,E11,F11)) -> 40 | L11: =MIN(G11,H11,IF(I11=0,H11,I11)) -> 45 | M11: =K11*J11 -> 1000 | N11: =L11*J11 -> 1125 | O11: =N11-M11 -> 125 | P11: =IF(O11>0,B11/O11,"No gain") -> 6 | Q11: Owned cleaner + finish; cleaner becomes bottleneck
A15: Personal upgrade | B15: Cash | C15: Base manual /h | D15: Upgraded manual /h | E15: Gain /h | F15: Active payback h
A16: Wide Brush | B16: =Assumptions!B14 -> 80 | C16: =Shops!R6 -> 1200 | D16: =Shops!D6*3600/(Assumptions!B15+Shops!F6) -> 1440 | E16: =D16-C16 -> 240 | F16: =IF(E16>0,B16/E16,"No gain") -> 0.33333333

Sheet Pacing
A1: HOW LONG UNTIL THE NEXT DOOR?
A2: Constant online activity scenario from Assumptions. Whole manual jobs, average bot income, base kits; no optional spending. Certification counts inside the local manual minimum. Later-shop outputs are placeholders.
A5: Milestone | B5: Cost | C5: Cash entering | D5: Manual cash/job | E5: Cycle sec | F5: Active share | G5: Manual cash/h | H5: Prior-chain auto cash/h | I5: Manual cash still needed? | J5: Manual jobs gate left | K5: Auto deliveries gate | L5: Local auto orders/h | M5: Hours needed (continuous) | N5: Manual jobs done | O5: Elapsed h rounded | P5: Manual income | Q5: Auto income | R5: Cash after purchase | S5: Total elapsed h
A6: Build Bonzi | B6: =Assumptions!B7 -> 100 | C6: =Assumptions!B6 -> 0 | D6: =Shops!D6 -> 20 | E6: =Shops!O6 -> 60 | F6: =Assumptions!B10 -> 1 | G6: =D6*3600/E6*F6 -> 1200 | H6: =0 -> 0 | I6: =MAX(0,B6-C6) -> 100 | J6: =Assumptions!B8 -> 3 | K6: =0 -> 0 | L6: =0 -> 0 | M6: =MAX(I6/(G6+H6),J6*E6/(3600*F6),IF(K6=0,0,K6/MAX(L6,0.000001))) -> 0.083333333 | N6: =ROUNDUP(ROUND(M6*3600*F6/E6,9),0) -> 5 | O6: =MAX(N6*E6/(3600*F6),IF(K6=0,0,K6/MAX(L6,0.000001))) -> 0.083333333 | P6: =N6*D6 -> 100 | Q6: =O6*H6 -> 0 | R6: =C6+P6+Q6-B6 -> 0 | S6: =SUM(O$6:O6) -> 0.083333333
A7: Open Busy High Street | B7: =Shops!C7 -> 600 | C7: =R6 -> 0 | D7: =Shops!D6 -> 20 | E7: =Shops!O6 -> 60 | F7: =Assumptions!B10 -> 1 | G7: =D7*3600/E7*F7 -> 1200 | H7: =SUM(Shops!Q$6:Q6) -> 300 | I7: =MAX(0,B7-C7) -> 600 | J7: =MAX(0,Shops!K7-N6) -> 10 | K7: =Shops!L7 -> 5 | L7: =Shops!P6 -> 30 | M7: =MAX(I7/(G7+H7),J7*E7/(3600*F7),IF(K7=0,0,K7/MAX(L7,0.000001))) -> 0.4 | N7: =ROUNDUP(ROUND(M7*3600*F7/E7,9),0) -> 24 | O7: =MAX(N7*E7/(3600*F7),IF(K7=0,0,K7/MAX(L7,0.000001))) -> 0.4 | P7: =N7*D7 -> 480 | Q7: =O7*H7 -> 120 | R7: =C7+P7+Q7-B7 -> 0 | S7: =SUM(O$6:O7) -> 0.48333333
A8: Open Restoration Studio | B8: =Shops!C8 -> 6000 | C8: =R7 -> 0 | D8: =Shops!D7 -> 60 | E8: =Shops!O7 -> 70 | F8: =Assumptions!B10 -> 1 | G8: =D8*3600/E8*F8 -> 3085.7143 | H8: =SUM(Shops!Q$6:Q7) -> 1050 | I8: =MAX(0,B8-C8) -> 6000 | J8: =MAX(0,Shops!K8) -> 12 | K8: =Shops!L8 -> 20 | L8: =Shops!P7 -> 30 | M8: =MAX(I8/(G8+H8),J8*E8/(3600*F8),IF(K8=0,0,K8/MAX(L8,0.000001))) -> 1.4507772 | N8: =ROUNDUP(ROUND(M8*3600*F8/E8,9),0) -> 75 | O8: =MAX(N8*E8/(3600*F8),IF(K8=0,0,K8/MAX(L8,0.000001))) -> 1.4583333 | P8: =N8*D8 -> 4500 | Q8: =O8*H8 -> 1531.25 | R8: =C8+P8+Q8-B8 -> 31.25 | S8: =SUM(O$6:O8) -> 1.9416667
A9: Open Commercial Workshop | B9: =Shops!C9 -> 40000 | C9: =R8 -> 31.25 | D9: =Shops!D8 -> 150 | E9: =Shops!O8 -> 110 | F9: =Assumptions!B10 -> 1 | G9: =D9*3600/E9*F9 -> 4909.0909 | H9: =SUM(Shops!Q$6:Q8) -> 2610 | I9: =MAX(0,B9-C9) -> 39968.75 | J9: =MAX(0,Shops!K9) -> 15 | K9: =Shops!L9 -> 30 | L9: =Shops!P8 -> 24 | M9: =MAX(I9/(G9+H9),J9*E9/(3600*F9),IF(K9=0,0,K9/MAX(L9,0.000001))) -> 5.315636 | N9: =ROUNDUP(ROUND(M9*3600*F9/E9,9),0) -> 174 | O9: =MAX(N9*E9/(3600*F9),IF(K9=0,0,K9/MAX(L9,0.000001))) -> 5.3166667 | P9: =N9*D9 -> 26100 | Q9: =O9*H9 -> 13876.5 | R9: =C9+P9+Q9-B9 -> 7.75 | S9: =SUM(O$6:O9) -> 7.2583333
A10: Open Flagship Atelier | B10: =Shops!C10 -> 180000 | C10: =R9 -> 7.75 | D10: =Shops!D9 -> 350 | E10: =Shops!O9 -> 140 | F10: =Assumptions!B10 -> 1 | G10: =D10*3600/E10*F10 -> 9000 | H10: =SUM(Shops!Q$6:Q9) -> 6810 | I10: =MAX(0,B10-C10) -> 179992.25 | J10: =MAX(0,Shops!K10) -> 18 | K10: =Shops!L10 -> 40 | L10: =Shops!P9 -> 24 | M10: =MAX(I10/(G10+H10),J10*E10/(3600*F10),IF(K10=0,0,K10/MAX(L10,0.000001))) -> 11.384709 | N10: =ROUNDUP(ROUND(M10*3600*F10/E10,9),0) -> 293 | O10: =MAX(N10*E10/(3600*F10),IF(K10=0,0,K10/MAX(L10,0.000001))) -> 11.394444 | P10: =N10*D10 -> 102550 | Q10: =O10*H10 -> 77596.167 | R10: =C10+P10+Q10-B10 -> 153.91667 | S10: =SUM(O$6:O10) -> 18.652778

Sheet Starter Routes
A1: THREE WAYS TO REACH HIGH STREET
A2: Routes start at launch, buy Bonzi first, skip optional upgrades. Guided return does only the required manual jobs and then waits. Continuous route estimates use average routine income.
A5: Route | B5: Active share after Bonzi | C5: Bonzi minute | D5: Post-Bonzi jobs | E5: Post-Bonzi active/online min | F5: Away min | G5: Total elapsed min | H5: Cash remaining | I5: Interpretation
A6: Keep cleaning | B6: =1 -> 1 | C6: =Pacing!N6*Shops!O6/60 -> 5 | D6: =ROUNDUP(ROUND(MAX(MAX(0,Shops!C7-Pacing!R6)/(Shops!R6*B6+Shops!Q6),MAX(0,Shops!K7-Pacing!N6)*Shops!O6/(3600*B6),Shops!L7/Shops!P6)*3600*B6/Shops!O6,9),0) -> 24 | E6: =D6*Shops!O6/(60*B6) -> 24 | F6: =0 -> 0 | G6: =C6+E6+F6 -> 29 | H6: =Pacing!R6+D6*Shops!D6+(E6+F6)*Shops!Q6/60-Shops!C7 -> 0 | I6: 29 jobs total; 12 bot deliveries after purchase at defaults.
A7: Half-time activity | B7: =Assumptions!B16 -> 0.5 | C7: =Pacing!N6*Shops!O6/60 -> 5 | D7: =ROUNDUP(ROUND(MAX(MAX(0,Shops!C7-Pacing!R6)/(Shops!R6*B7+Shops!Q6),MAX(0,Shops!K7-Pacing!N6)*Shops!O6/(3600*B7),Shops!L7/Shops!P6)*3600*B7/Shops!O6,9),0) -> 20 | E7: =D7*Shops!O6/(60*B7) -> 40 | F7: =0 -> 0 | G7: =C7+E7+F7 -> 45 | H7: =Pacing!R6+D7*Shops!D6+(E7+F7)*Shops!Q6/60-Shops!C7 -> 0 | I7: 25 jobs total; slower manual activity, more routine income.
A8: Minimum work, then return | B8: =1 -> 1 | C8: =Pacing!N6*Shops!O6/60 -> 5 | D8: =MAX(0,Shops!K7-Pacing!N6) -> 10 | E8: =D8*Shops!O6/60 -> 10 | F8: =MAX(0,(Shops!C7-Pacing!R6-D8*Shops!D6-E8*Shops!Q6/60)/(Shops!Q6/60),Shops!L7/Shops!P6*60-E8) -> 70 | G8: =C8+E8+F8 -> 85 | H8: =Pacing!R6+D8*Shops!D6+(E8+F8)*Shops!Q6/60-Shops!C7 -> 0 | I8: 15 jobs total. If away time exceeds cap, multiple return intervals are needed.

Sheet Offline
A1: WHAT HAPPENS WHILE YOU ARE AWAY
A2: Whole automatic orders pay; fractional order progress carries forward. Ownership switch means the branch already existed and its automation was enabled at departure. No upgrade/new shop is applied retrospectively.
A5: Shop | B5: Owned + enabled (0/1) | C5: Away hours | D5: Credited hours | E5: Auto orders/h | F5: Cash/order | G5: Order remainder entering | H5: Completed orders | I5: Cash earned | J5: Order remainder leaving
A6: Neighborhood Shop | B6: 1 | C6: 8 | D6: =IF(B6=1,MIN(MAX(0,C6),Assumptions!B9),0) -> 8 | E6: =Shops!P6 -> 30 | F6: =Shops!J6 -> 10 | G6: 0 | H6: =IF(B6=1,ROUNDDOWN(ROUND(D6*E6+G6,9),0),0) -> 240 | I6: =H6*F6 -> 2400 | J6: =IF(B6=1,ROUND(D6*E6+G6-H6,9),G6) -> 0
A7: Busy High Street | B7: 1 | C7: 8 | D7: =IF(B7=1,MIN(MAX(0,C7),Assumptions!B9),0) -> 8 | E7: =Shops!P7 -> 30 | F7: =Shops!J7 -> 25 | G7: 0 | H7: =IF(B7=1,ROUNDDOWN(ROUND(D7*E7+G7,9),0),0) -> 240 | I7: =H7*F7 -> 6000 | J7: =IF(B7=1,ROUND(D7*E7+G7-H7,9),G7) -> 0
A8: Restoration Studio | B8: 0 | C8: 8 | D8: =IF(B8=1,MIN(MAX(0,C8),Assumptions!B9),0) -> 0 | E8: =Shops!P8 -> 24 | F8: =Shops!J8 -> 65 | G8: 0 | H8: =IF(B8=1,ROUNDDOWN(ROUND(D8*E8+G8,9),0),0) -> 0 | I8: =H8*F8 -> 0 | J8: =IF(B8=1,ROUND(D8*E8+G8-H8,9),G8) -> 0
A9: Commercial Workshop | B9: 0 | C9: 8 | D9: =IF(B9=1,MIN(MAX(0,C9),Assumptions!B9),0) -> 0 | E9: =Shops!P9 -> 24 | F9: =Shops!J9 -> 175 | G9: 0 | H9: =IF(B9=1,ROUNDDOWN(ROUND(D9*E9+G9,9),0),0) -> 0 | I9: =H9*F9 -> 0 | J9: =IF(B9=1,ROUND(D9*E9+G9-H9,9),G9) -> 0
A10: Flagship Atelier | B10: 0 | C10: 8 | D10: =IF(B10=1,MIN(MAX(0,C10),Assumptions!B9),0) -> 0 | E10: =Shops!P10 -> 20 | F10: =Shops!J10 -> 450 | G10: 0 | H10: =IF(B10=1,ROUNDDOWN(ROUND(D10*E10+G10,9),0),0) -> 0 | I10: =H10*F10 -> 0 | J10: =IF(B10=1,ROUND(D10*E10+G10-H10,9),G10) -> 0
A12: TOTAL CLAIM | I12: =SUM(I6:I10) -> 8400
A14: Cap behavior | B14: Cap truncates simulated absence time, not the wallet. New store clocks start on purchase. Negative elapsed time earns zero. Reopening cannot award a previously settled interval again.

Sheet Blueprints & Parts
A1: PERMANENT KNOWLEDGE, USEFUL PARTS
A2: No research fragments. All required blueprints and capabilities are guaranteed. Parts begin in High Street and are optional for expansion.
A5: Design / rule | B5: Unlock requirement | C5: Cash cost | D5: Parts cost | E5: Consumption / result
A6: Bonzi | B6: 3 paid S1 manual jobs | C6: =Items!C7 -> 100 | D6: 0 | E6: Whole blueprint permanent; cash builds companion + local unit.
A7: Wide Brush | B7: 8 paid S1 manual jobs | C7: =Items!C8 -> 80 | D7: 0 | E7: Whole blueprint permanent; optional personal build.
A8: S1 Mk II | B8: 10 paid S1 manual jobs; Bonzi built | C8: =Upgrades!B6 -> 120 | D8: =Upgrades!C6 -> 0 | E8: Local module; first bot improvement teaches cash-only upgrades.
A9: S1 intake | B9: 10 paid S1 manual jobs; Bonzi built | C9: =Upgrades!B7 -> 100 | D9: =Upgrades!C7 -> 0 | E9: Local capacity upgrade; can be bought before Mk II but preview zero gain.
A10: S2 starter kit | B10: Buy S2 | C10: Included | D10: 0 | E10: Jet, squeegee, basic local unit and finishing station usable immediately.
A11: S2 cleaner | B11: 6 paid S2 manual jobs | C11: =Upgrades!B9 -> 900 | D11: =Upgrades!C9 -> 6 | E11: Optional; subtract six parts on successful build only.
A12: S2 finishing | B12: 6 paid S2 manual jobs | C12: =Upgrades!B10 -> 600 | D12: =Upgrades!C10 -> 4 | E12: Optional; may be bought before cleaner; Upgrades shows a suggested sequence.
A13: S2 intake | B13: 6 paid S2 manual jobs | C13: =Upgrades!B11 -> 750 | D13: =Upgrades!C11 -> 0 | E13: Optional; no parts consumed.
A14: Parts source | B14: Each paid manual job in S2+ | C14: N/A | D14: =Assumptions!B13 -> 1 | E14: Integer award. No parts from idle, S1 or free replay.
A15: Duplicate blueprint | B15: Repeated milestone/load | C15: N/A | D15: 0 | E15: No-op; grant ID prevents duplication. No conversion currency.
A16: Later mandatory kits | B16: Respective shop purchase | C16: Included | D16: 0 | E16: Necessary capability never depends on an optional module or random drop.
A19: Parts budget example | B19: Eligible S2+ jobs | C19: Parts earned | D19: Parts spent | E19: Parts remaining
A20: Build S2 cleaner | B20: 6 | C20: =B20*Assumptions!B13 -> 6 | D20: =Upgrades!C9 -> 6 | E20: =C20-D20 -> 0
A21: Then finishing | B21: 4 | C21: =B21*Assumptions!B13 -> 4 | D21: =Upgrades!C10 -> 4 | E21: =E20+C21-D21 -> 0

Sheet UI & States
A1: THE NEXT UI PASS
A2: This is a design specification, not an implemented game UI. Expose only the next meaningful decision.
A5: Surface / system | B5: States | C5: Action | D5: Guard / saved outcome
A6: Contract | B6: Offered → in progress → finish-ready → paid | C6: Start / resume / Finish | D6: Both cleaning thresholds required. Persist masks/job ID. One payout and local count per job.
A7: Bonzi card | B7: Hidden → blueprint known → affordable → built | C7: Build Bonzi | D7: Blueprint and cash checked; debit once; start automation at purchase timestamp.
A8: Upgrade card | B8: Blueprint locked / known / affordable / owned | C8: Build or upgrade | D8: Show exact before/after gain and limiting station. Debit cash/parts atomically.
A9: Shop expansion | B9: Hidden → revealed → eligible → affordable → owned | C9: Open shop | D9: Local service counts and certification, Bonzi for S2, and cash. One summary includes kit and remaining cash.
A10: Owned-shop selector | B10: Current / owned inactive | C10: Visit shop | D10: Free view change. Keep old branches producing. Preserve one chain-wide active personal job.
A11: Active job during move | B11: In progress / paused | C11: Finish or explicitly pause | D11: No second manual job until resumed job completes or is abandoned. No abandonment reward/reroll.
A12: Return summary | B12: No earnings / claimable / capped | C12: Collect once | D12: Settle past interval once, preserving fractional orders. Offline is not extra income over online.
A13: Parts display | B13: Hidden until S2 / visible | C13: View module costs | D13: Only one parts type. No inventory cap, expiry, passive source or mandatory use.
A14: Purchase recovery | B14: Ready / saving / committed / failed | C14: Single transaction | D14: Validate again at commit; prevent negative wallet and repeat taps; no duplicate kit or charge after reload.
A15: Production | B15: Not enabled / demand limited / cleaner limited / finish limited | C15: Inspect bottleneck | D15: Separate manual and routine pools. Settle old rate before module or price changes.

Sheet Checks
A1: MODEL CHECKS & PLAYTEST HANDOFF
A2: Formula checks update when inputs recalculate. Discrete simulation below is a default-only verification, not a dynamic workbook simulation. Test game save/reward behavior separately when implemented.
A5: Check | B5: Actual | C5: Expected / condition | D5: Result
A6: Starter premises have no price | B6: =Shops!C6 -> 0 | C6: =0 -> 0 | D6: =IF(B6=0,"PASS","REVIEW") -> PASS
A7: Bonzi first-route cash is nonnegative | B7: =Pacing!R6 -> 0 | C7: >=0 | D7: =IF(B7>=0,"PASS","REVIEW") -> PASS
A8: S2 route cash is nonnegative | B8: =Pacing!R7 -> 0 | C8: >=0 | D8: =IF(B8>=0,"PASS","REVIEW") -> PASS
A9: S1 intake-first output gain | B9: =Upgrades!O8 -> 0 | C9: =0 -> 0 | D9: =IF(B9=0,"PASS","REVIEW") -> PASS
A10: All modeled purchase wallets stay nonnegative | B10: =MIN(Pacing!R6:R10) -> 0 | C10: >=0 | D10: =IF(B10>=0,"PASS","REVIEW") -> PASS
A11: No offline remainder outside [0,1) | B11: =IF(AND(MIN(Offline!J6:J10)>=0,MAX(Offline!J6:J10)<1),1,0) -> 1 | C11: =1 -> 0 | D11: =IF(B11=1,"PASS","REVIEW") -> PASS
A12: Guided return fits one offline interval | B12: =IF('Starter Routes'!F8<=Assumptions!B9*60,1,0) -> 1 | C12: =1 -> 0 | D12: =IF(B12=1,"PASS","REVIEW") -> PASS
A13: Parts example never overspends | B13: =MIN('Blueprints & Parts'!E20:E21) -> 0 | C13: >=0 | D13: =IF(B13>=0,"PASS","REVIEW") -> PASS
A14: Bonzi route meets blueprint gate | B14: =Pacing!N6-Assumptions!B8 -> 2 | C14: >=0 | D14: =IF(B14>=0,"PASS","REVIEW") -> PASS
A15: Opening paid-job count is sufficient | B15: =Pacing!N6+Pacing!N7-Shops!K7 -> 14 | C15: >=0 | D15: =IF(B15>=0,"PASS","REVIEW") -> PASS
A18: Default discrete event simulation
A19: Bonzi purchase minute | B19: 5 | C19: 100 cash after 5 full jobs | D19: PASS
A20: High Street opening minute | B20: 29 | C20: 29 jobs, 12 bot deliveries, 0 cash left | D20: PASS
A21: Model sensitivity | B21: Change work sec 50→110 | C21: Bonzi becomes 10 min; replay route, do not retain timing claims | D21: PLAYTEST
A22: Runtime tests needed | B22: Not implemented | C22: Repeat Finish, double-buy, resume, old-shop income, negative clock, offline cap | D22: TODO
